{
  "entityId": "entity-modelportfolio",
  "queryId": "query-active-only",
  "totalCount": 526,
  "pageSize": 25,
  "currentPage": 1,
  "records": [
    {
      "id": "66042bcb-e489-4145-a944-6de77f1f15d0",
      "name": "Configurable directional function 1",
      "status": "Inactive",
      "createdDate": "2025-11-05T13:32:09",
      "updatedDate": "2026-01-24T09:00:15",
      "owner": "Kimberly Gonzales",
      "type": "Premium",
      "category": "Type C",
      "value": 4327.17,
      "description": "Possible return tax."
    },
    {
      "id": "621b70ec-ed0b-4fe8-978f-50b52988d383",
      "name": "Streamlined upward-trending knowledgebase 2",
      "status": "Inactive",
      "createdDate": "2025-03-14T17:36:28",
      "updatedDate": "2026-02-08T09:58:04",
      "owner": "Jenna Snyder",
      "type": "Premium",
      "category": "Type B",
      "value": 233.67,
      "description": "Maybe effect sister."
    },
    {
      "id": "3336967b-71d0-4637-9696-5289edd59d87",
      "name": "User-centric encompassing protocol 3",
      "status": "Completed",
      "createdDate": "2025-05-26T18:52:36",
      "updatedDate": "2026-02-17T05:36:06",
      "owner": "Diana Malone",
      "type": "Basic",
      "category": "Type A",
      "value": 8273.44,
      "description": "Each describe rather hundred way book."
    },
    {
      "id": "e69617b9-3d8a-4c8a-bb56-93231d5e1eb2",
      "name": "Compatible fresh-thinking throughput 4",
      "status": "Pending",
      "createdDate": "2025-03-07T01:17:14",
      "updatedDate": "2026-01-22T01:53:10",
      "owner": "Andrew Hutchinson",
      "type": "Basic",
      "category": "Type A",
      "value": 7869.94,
      "description": "Role customer quite several ago catch page foot."
    },
    {
      "id": "377aa43a-6d04-49b5-b09b-7f18c98788de",
      "name": "Fundamental transitional access 5",
      "status": "Inactive",
      "createdDate": "2026-01-24T00:52:59",
      "updatedDate": "2026-01-26T07:16:21",
      "owner": "Alexandria Carter",
      "type": "Basic",
      "category": "Type B",
      "value": 2709.44,
      "description": "Family college travel kid everything specific."
    },
    {
      "id": "d6e31cf3-c104-42ca-b6ee-68c5ee882809",
      "name": "Synergistic client-server task-force 6",
      "status": "Inactive",
      "createdDate": "2025-11-05T10:52:04",
      "updatedDate": "2026-01-28T06:00:41",
      "owner": "Mr. Daniel Moore",
      "type": "Standard",
      "category": "Type B",
      "value": 1094.21,
      "description": "Consider there health."
    },
    {
      "id": "591ab018-cee3-4bef-990e-75ede3609213",
      "name": "Fully-configurable web-enabled secured line 7",
      "status": "Inactive",
      "createdDate": "2025-09-08T08:43:57",
      "updatedDate": "2026-01-25T21:20:28",
      "owner": "Heather Allen",
      "type": "Premium",
      "category": "Type A",
      "value": 3499.79,
      "description": "Win most know western control."
    },
    {
      "id": "5d649b77-723f-4696-bb72-e764d38e2459",
      "name": "Stand-alone web-enabled core 8",
      "status": "Completed",
      "createdDate": "2025-11-12T04:13:11",
      "updatedDate": "2026-02-05T23:14:06",
      "owner": "Kenneth Hughes",
      "type": "Standard",
      "category": "Type A",
      "value": 9420.07,
      "description": "West despite dog agree see enough dinner."
    },
    {
      "id": "24a7c996-ea66-49a7-b86d-b9ddb691d59a",
      "name": "Programmable even-keeled portal 9",
      "status": "Active",
      "createdDate": "2026-02-15T10:01:22",
      "updatedDate": "2026-01-18T18:17:30",
      "owner": "Cameron Edwards",
      "type": "Premium",
      "category": "Type A",
      "value": 1053.53,
      "description": "All major race life eye realize."
    },
    {
      "id": "0604f6c2-1197-4f05-8d9d-fad01733d139",
      "name": "Centralized full-range leverage 10",
      "status": "Inactive",
      "createdDate": "2025-04-13T16:31:18",
      "updatedDate": "2026-01-31T10:16:59",
      "owner": "Suzanne Vincent",
      "type": "Premium",
      "category": "Type B",
      "value": 6837.36,
      "description": "Toward hard development add quickly wide himself."
    },
    {
      "id": "19b4ade0-a960-410f-a0f2-9f7792e0abea",
      "name": "Profit-focused logistical migration 11",
      "status": "Completed",
      "createdDate": "2025-10-31T12:42:27",
      "updatedDate": "2026-02-12T14:46:04",
      "owner": "Andrew Pacheco",
      "type": "Basic",
      "category": "Type A",
      "value": 3112.64,
      "description": "Various today recently by."
    },
    {
      "id": "df9af288-9c52-48e2-9023-662078ec5d1d",
      "name": "Advanced dedicated forecast 12",
      "status": "Pending",
      "createdDate": "2025-10-27T19:48:39",
      "updatedDate": "2026-02-04T19:58:17",
      "owner": "John Nicholson",
      "type": "Basic",
      "category": "Type B",
      "value": 4386.27,
      "description": "Exist base painting certainly themselves."
    },
    {
      "id": "6a583d82-8766-40d2-9445-28a3c3f03fb9",
      "name": "Grass-roots dynamic monitoring 13",
      "status": "Pending",
      "createdDate": "2025-11-09T21:12:32",
      "updatedDate": "2026-01-30T04:09:56",
      "owner": "Rachel Maldonado",
      "type": "Basic",
      "category": "Type A",
      "value": 609.99,
      "description": "Discover reason why end."
    },
    {
      "id": "d6001f3a-7d4d-4cde-a82c-cba9b7e90ef5",
      "name": "Devolved encompassing emulation 14",
      "status": "Completed",
      "createdDate": "2025-12-06T20:40:30",
      "updatedDate": "2026-01-25T21:19:53",
      "owner": "Steven Watson",
      "type": "Basic",
      "category": "Type B",
      "value": 9886.84,
      "description": "Tough move trouble account minute since three third."
    },
    {
      "id": "10f4e7a0-eb6d-45c6-9c12-1c0db66439e7",
      "name": "Integrated intangible array 15",
      "status": "Pending",
      "createdDate": "2025-07-09T01:22:30",
      "updatedDate": "2026-02-14T12:51:47",
      "owner": "Ian Casey",
      "type": "Premium",
      "category": "Type A",
      "value": 1868.2,
      "description": "Guess note per floor feeling southern."
    },
    {
      "id": "7517a113-6fd1-4d35-b294-ff9afbe0f8c5",
      "name": "Up-sized eco-centric parallelism 16",
      "status": "Active",
      "createdDate": "2026-02-03T22:30:23",
      "updatedDate": "2026-01-20T01:26:12",
      "owner": "Amanda Taylor",
      "type": "Standard",
      "category": "Type A",
      "value": 7705.55,
      "description": "Big draw upon church."
    },
    {
      "id": "91534063-1e17-46e0-b593-1d6ab413c749",
      "name": "Vision-oriented multi-state website 17",
      "status": "Completed",
      "createdDate": "2025-07-30T06:43:24",
      "updatedDate": "2026-02-02T14:04:33",
      "owner": "Teresa Barker",
      "type": "Basic",
      "category": "Type C",
      "value": 7842.24,
      "description": "Picture Democrat sing enter probably product structure spend."
    },
    {
      "id": "570a0a68-4031-4617-a699-300a0cd32c0a",
      "name": "Assimilated zero-defect analyzer 18",
      "status": "Active",
      "createdDate": "2025-08-07T00:41:09",
      "updatedDate": "2026-01-24T16:59:35",
      "owner": "Roy Fischer",
      "type": "Basic",
      "category": "Type A",
      "value": 1842.05,
      "description": "Success western its ahead happy."
    },
    {
      "id": "9152c587-57de-4941-a584-10e01a512755",
      "name": "Versatile intermediate projection 19",
      "status": "Inactive",
      "createdDate": "2025-08-25T00:27:41",
      "updatedDate": "2026-02-06T00:44:04",
      "owner": "Kayla Curtis",
      "type": "Basic",
      "category": "Type B",
      "value": 847.59,
      "description": "Management high speak soldier first area."
    },
    {
      "id": "aa80008e-2584-4485-afd1-31ba22036b32",
      "name": "Secured directional system engine 20",
      "status": "Pending",
      "createdDate": "2025-08-05T18:46:12",
      "updatedDate": "2026-01-21T18:04:26",
      "owner": "Kevin Thompson",
      "type": "Standard",
      "category": "Type A",
      "value": 761.78,
      "description": "Above minute beautiful fill affect."
    },
    {
      "id": "41c790af-43d3-4eb5-b149-348725116e25",
      "name": "Optional multimedia orchestration 21",
      "status": "Active",
      "createdDate": "2025-05-12T02:23:14",
      "updatedDate": "2026-02-15T21:19:07",
      "owner": "Mr. Timothy Cruz DVM",
      "type": "Basic",
      "category": "Type C",
      "value": 2740.21,
      "description": "Certainly city those tell knowledge."
    },
    {
      "id": "acafa743-f928-4270-a6d4-9642ffa223b8",
      "name": "De-engineered attitude-oriented algorithm 22",
      "status": "Completed",
      "createdDate": "2026-02-15T15:20:37",
      "updatedDate": "2026-01-28T01:26:17",
      "owner": "Diana Hill",
      "type": "Premium",
      "category": "Type C",
      "value": 6783.58,
      "description": "Process pressure teacher bed."
    },
    {
      "id": "098841f4-d0e3-4d5d-8a82-bbf67cc6989e",
      "name": "Multi-lateral zero tolerance service-desk 23",
      "status": "Inactive",
      "createdDate": "2025-04-14T18:21:16",
      "updatedDate": "2026-01-25T21:21:16",
      "owner": "Kelli Peters",
      "type": "Standard",
      "category": "Type A",
      "value": 1806.08,
      "description": "Home imagine standard ask."
    },
    {
      "id": "912a0b18-5dbd-4c4c-8ce6-5ed738384809",
      "name": "Mandatory heuristic groupware 24",
      "status": "Inactive",
      "createdDate": "2025-03-15T18:06:05",
      "updatedDate": "2026-01-19T20:31:56",
      "owner": "Heather Horton",
      "type": "Standard",
      "category": "Type A",
      "value": 4546.87,
      "description": "Where build appear tell idea return unit."
    },
    {
      "id": "58c7f14b-10eb-4c9d-93eb-b8bd67c5e525",
      "name": "Realigned reciprocal circuit 25",
      "status": "Pending",
      "createdDate": "2025-07-16T13:08:44",
      "updatedDate": "2026-02-14T09:20:46",
      "owner": "Brittany Roman",
      "type": "Premium",
      "category": "Type A",
      "value": 4036.61,
      "description": "Just western against feeling red."
    }
  ],
  "schema": [
    {
      "fieldName": "id",
      "displayName": "Id",
      "dataType": "string",
      "isKey": true,
      "isRequired": true
    },
    {
      "fieldName": "name",
      "displayName": "Name",
      "dataType": "string",
      "isKey": false,
      "isRequired": true
    },
    {
      "fieldName": "status",
      "displayName": "Status",
      "dataType": "string",
      "isKey": false,
      "isRequired": true
    },
    {
      "fieldName": "createdDate",
      "displayName": "Createddate",
      "dataType": "date",
      "isKey": false,
      "isRequired": false
    },
    {
      "fieldName": "updatedDate",
      "displayName": "Updateddate",
      "dataType": "date",
      "isKey": false,
      "isRequired": false
    },
    {
      "fieldName": "owner",
      "displayName": "Owner",
      "dataType": "string",
      "isKey": false,
      "isRequired": false
    },
    {
      "fieldName": "type",
      "displayName": "Type",
      "dataType": "string",
      "isKey": false,
      "isRequired": false
    },
    {
      "fieldName": "category",
      "displayName": "Category",
      "dataType": "string",
      "isKey": false,
      "isRequired": false
    },
    {
      "fieldName": "value",
      "displayName": "Value",
      "dataType": "string",
      "isKey": false,
      "isRequired": false
    },
    {
      "fieldName": "description",
      "displayName": "Description",
      "dataType": "string",
      "isKey": false,
      "isRequired": false
    }
  ]
}