{
  "entityId": "entity-client",
  "queryId": "query-recent-updates",
  "totalCount": 931,
  "pageSize": 25,
  "currentPage": 1,
  "records": [
    {
      "id": "3b33c2a0-4394-48d8-ab0e-5c954607aef2",
      "name": "Streamlined full-range budgetary management 1",
      "status": "Completed",
      "createdDate": "2025-08-06T10:03:59",
      "updatedDate": "2026-01-29T10:45:48",
      "owner": "Joseph Dean PhD",
      "clientId": "CL-92902",
      "firstName": "David",
      "lastName": "Garcia",
      "email": "shawngreen@example.org",
      "phone": "939-736-8174",
      "aum": 6907525.72,
      "riskTolerance": "Moderate",
      "onboardDate": "2017-09-16"
    },
    {
      "id": "1fc07e10-d3d3-44ed-bccf-e0d6e43f3473",
      "name": "Versatile next generation product 2",
      "status": "Active",
      "createdDate": "2026-01-30T13:18:41",
      "updatedDate": "2026-02-13T20:24:59",
      "owner": "Michael Murray",
      "clientId": "CL-42672",
      "firstName": "Leslie",
      "lastName": "Hudson",
      "email": "carpenterrebecca@example.org",
      "phone": "+1-492-989-4534x555",
      "aum": 3191047.78,
      "riskTolerance": "Aggressive",
      "onboardDate": "2019-03-21"
    },
    {
      "id": "d806a075-fc75-4d78-978e-2e6d070975b4",
      "name": "Quality-focused user-facing matrices 3",
      "status": "Completed",
      "createdDate": "2025-09-10T09:37:20",
      "updatedDate": "2026-01-24T21:41:28",
      "owner": "Carmen Garner",
      "clientId": "CL-97438",
      "firstName": "Richard",
      "lastName": "Acosta",
      "email": "cmorris@example.org",
      "phone": "350.975.1084",
      "aum": 841102.67,
      "riskTolerance": "Aggressive",
      "onboardDate": "2024-06-15"
    },
    {
      "id": "127c2165-92db-4e2c-b01b-39d5a0d38afc",
      "name": "Triple-buffered executive policy 4",
      "status": "Pending",
      "createdDate": "2026-02-12T11:56:08",
      "updatedDate": "2026-02-10T14:49:30",
      "owner": "Michael Johnson",
      "clientId": "CL-31573",
      "firstName": "William",
      "lastName": "Smith",
      "email": "hward@example.com",
      "phone": "444.270.2436",
      "aum": 11749459.94,
      "riskTolerance": "Moderate",
      "onboardDate": "2017-06-07"
    },
    {
      "id": "fbe31af2-c48e-4119-b92b-8f88c0554202",
      "name": "Seamless well-modulated firmware 5",
      "status": "Inactive",
      "createdDate": "2025-09-01T14:14:54",
      "updatedDate": "2026-02-08T05:15:23",
      "owner": "Robert Morgan",
      "clientId": "CL-84127",
      "firstName": "Tyler",
      "lastName": "Rojas",
      "email": "zmccoy@example.org",
      "phone": "581-544-8722x6423",
      "aum": 1978972.66,
      "riskTolerance": "Aggressive",
      "onboardDate": "2019-06-23"
    },
    {
      "id": "d7b16ef6-69c3-4715-943a-d40a7d14349d",
      "name": "Synchronized eco-centric emulation 6",
      "status": "Pending",
      "createdDate": "2025-03-17T02:59:07",
      "updatedDate": "2026-01-29T18:53:46",
      "owner": "Sherry Martinez",
      "clientId": "CL-26124",
      "firstName": "Kimberly",
      "lastName": "Roth",
      "email": "elizabethflynn@example.com",
      "phone": "2997118357",
      "aum": 18149741.45,
      "riskTolerance": "Moderate",
      "onboardDate": "2023-10-21"
    },
    {
      "id": "1d58c8df-8b67-4bb7-8374-428310328b37",
      "name": "Expanded intangible monitoring 7",
      "status": "Inactive",
      "createdDate": "2025-12-08T09:33:57",
      "updatedDate": "2026-01-23T08:43:54",
      "owner": "Kendra Rojas",
      "clientId": "CL-47442",
      "firstName": "Jeffery",
      "lastName": "Brown",
      "email": "marcus10@example.net",
      "phone": "9002827647",
      "aum": 9154006.69,
      "riskTolerance": "Aggressive",
      "onboardDate": "2018-09-30"
    },
    {
      "id": "1ba5b9fb-41a0-4255-afd7-cdaec79a708d",
      "name": "Proactive methodical focus group 8",
      "status": "Completed",
      "createdDate": "2025-06-16T19:22:25",
      "updatedDate": "2026-01-21T08:41:50",
      "owner": "Jennifer Rich",
      "clientId": "CL-51326",
      "firstName": "Martin",
      "lastName": "Fisher",
      "email": "freytraci@example.org",
      "phone": "(514)723-2769x3261",
      "aum": 5086839.92,
      "riskTolerance": "Conservative",
      "onboardDate": "2019-05-12"
    },
    {
      "id": "240e5a67-ae65-4a1c-967b-4d7e5ddf5f22",
      "name": "Exclusive asymmetric throughput 9",
      "status": "Pending",
      "createdDate": "2025-09-11T02:02:12",
      "updatedDate": "2026-02-07T16:24:08",
      "owner": "Stephanie Hill",
      "clientId": "CL-77172",
      "firstName": "James",
      "lastName": "Wright",
      "email": "casey12@example.org",
      "phone": "(824)788-1393x9315",
      "aum": 19913270.15,
      "riskTolerance": "Conservative",
      "onboardDate": "2019-11-22"
    },
    {
      "id": "1596232e-e6e2-423e-9eda-ad03710f1134",
      "name": "Switchable zero tolerance benchmark 10",
      "status": "Completed",
      "createdDate": "2025-09-24T15:41:59",
      "updatedDate": "2026-01-21T05:39:05",
      "owner": "Mary Barnes",
      "clientId": "CL-56209",
      "firstName": "Frank",
      "lastName": "Chung",
      "email": "samanthasavage@example.net",
      "phone": "(202)630-1486x98611",
      "aum": 1570617.23,
      "riskTolerance": "Moderate",
      "onboardDate": "2019-08-02"
    },
    {
      "id": "ce009089-afb9-4302-8b0f-3bd3e144ba17",
      "name": "Diverse 24hour application 11",
      "status": "Pending",
      "createdDate": "2025-05-15T09:19:24",
      "updatedDate": "2026-02-07T02:41:25",
      "owner": "Regina Jacobs",
      "clientId": "CL-22405",
      "firstName": "Jeremy",
      "lastName": "Ellis",
      "email": "bross@example.net",
      "phone": "(338)601-7029",
      "aum": 10878631.09,
      "riskTolerance": "Moderate",
      "onboardDate": "2022-06-21"
    },
    {
      "id": "168304f0-daf5-47c2-bfcd-1ea8b6c4bc5b",
      "name": "Progressive zero tolerance challenge 12",
      "status": "Pending",
      "createdDate": "2025-07-08T20:53:40",
      "updatedDate": "2026-01-20T04:23:32",
      "owner": "Thomas Anthony",
      "clientId": "CL-73293",
      "firstName": "Richard",
      "lastName": "Kelly",
      "email": "courtney15@example.net",
      "phone": "381-973-7408x828",
      "aum": 8345105.32,
      "riskTolerance": "Moderate",
      "onboardDate": "2020-01-06"
    },
    {
      "id": "c039606e-8ced-483e-bc77-f058ed973a5f",
      "name": "Face-to-face needs-based ability 13",
      "status": "Pending",
      "createdDate": "2025-04-25T19:09:45",
      "updatedDate": "2026-01-30T04:17:45",
      "owner": "Amber Young",
      "clientId": "CL-91328",
      "firstName": "Pamela",
      "lastName": "Stafford",
      "email": "perezlindsay@example.net",
      "phone": "(958)977-4982",
      "aum": 5651501.22,
      "riskTolerance": "Moderate",
      "onboardDate": "2018-01-16"
    },
    {
      "id": "3f5f3e28-6349-4e4f-a11e-50988fb4ddeb",
      "name": "Extended stable emulation 14",
      "status": "Pending",
      "createdDate": "2025-06-18T01:02:41",
      "updatedDate": "2026-01-24T02:48:23",
      "owner": "Courtney Walker",
      "clientId": "CL-81104",
      "firstName": "Vanessa",
      "lastName": "Martinez",
      "email": "mossharold@example.org",
      "phone": "716.515.5414",
      "aum": 15616965.65,
      "riskTolerance": "Conservative",
      "onboardDate": "2018-12-29"
    },
    {
      "id": "d9588589-1922-4763-af85-a8334d118c20",
      "name": "Digitized clear-thinking capability 15",
      "status": "Inactive",
      "createdDate": "2025-12-07T06:30:40",
      "updatedDate": "2026-02-02T05:15:15",
      "owner": "Kyle Ramirez",
      "clientId": "CL-46844",
      "firstName": "Susan",
      "lastName": "Johnson",
      "email": "higginsbrian@example.net",
      "phone": "001-385-980-1664",
      "aum": 16571976.34,
      "riskTolerance": "Moderate",
      "onboardDate": "2023-12-18"
    },
    {
      "id": "7641b429-4529-4559-9d64-9ca96c63e8d6",
      "name": "Mandatory well-modulated matrices 16",
      "status": "Active",
      "createdDate": "2025-06-05T05:53:05",
      "updatedDate": "2026-02-15T05:53:16",
      "owner": "Jeffrey Barnett",
      "clientId": "CL-78099",
      "firstName": "David",
      "lastName": "Clark",
      "email": "rachel17@example.org",
      "phone": "959-776-4929",
      "aum": 18897341.95,
      "riskTolerance": "Moderate",
      "onboardDate": "2022-09-22"
    },
    {
      "id": "dcfa9547-cb9e-4116-9c09-a7ced5ed059b",
      "name": "Fundamental 5thgeneration adapter 17",
      "status": "Completed",
      "createdDate": "2025-09-06T09:19:26",
      "updatedDate": "2026-02-03T11:34:38",
      "owner": "Hannah Williams",
      "clientId": "CL-64539",
      "firstName": "Tonya",
      "lastName": "Wang",
      "email": "adamsdavid@example.org",
      "phone": "639.476.4067x096",
      "aum": 861346.49,
      "riskTolerance": "Conservative",
      "onboardDate": "2018-01-03"
    },
    {
      "id": "5769c5a2-ad89-4ca5-95e0-3dfcc3b8de41",
      "name": "Integrated object-oriented success 18",
      "status": "Active",
      "createdDate": "2025-11-30T07:05:17",
      "updatedDate": "2026-02-04T06:12:10",
      "owner": "Richard Nolan",
      "clientId": "CL-83419",
      "firstName": "Michael",
      "lastName": "Duke",
      "email": "tammy62@example.org",
      "phone": "001-567-720-5475x07347",
      "aum": 9167564.79,
      "riskTolerance": "Aggressive",
      "onboardDate": "2021-11-11"
    },
    {
      "id": "6b08b7ff-896d-458d-b703-526be7301792",
      "name": "Vision-oriented high-level customer loyalty 19",
      "status": "Inactive",
      "createdDate": "2025-04-26T03:01:04",
      "updatedDate": "2026-02-14T13:52:15",
      "owner": "Anthony Barber",
      "clientId": "CL-97862",
      "firstName": "Rachel",
      "lastName": "Ward",
      "email": "keith32@example.net",
      "phone": "4642612956",
      "aum": 18008581.68,
      "riskTolerance": "Conservative",
      "onboardDate": "2016-03-29"
    },
    {
      "id": "f37f18d8-5abe-4346-856a-8ba087e7630c",
      "name": "Quality-focused asynchronous productivity 20",
      "status": "Inactive",
      "createdDate": "2025-10-08T13:51:08",
      "updatedDate": "2026-01-31T09:01:01",
      "owner": "Michelle Ewing",
      "clientId": "CL-54518",
      "firstName": "James",
      "lastName": "Tyler",
      "email": "perkinslaura@example.com",
      "phone": "645-257-3189x64859",
      "aum": 5842757.46,
      "riskTolerance": "Aggressive",
      "onboardDate": "2019-06-27"
    },
    {
      "id": "dc69f3ea-3df2-4283-8211-173b624c3109",
      "name": "Right-sized background customer loyalty 21",
      "status": "Inactive",
      "createdDate": "2025-04-07T06:38:37",
      "updatedDate": "2026-02-06T10:29:20",
      "owner": "Hannah Valenzuela",
      "clientId": "CL-94274",
      "firstName": "Robert",
      "lastName": "Armstrong",
      "email": "joshuasmith@example.net",
      "phone": "9427517919",
      "aum": 14293383.39,
      "riskTolerance": "Aggressive",
      "onboardDate": "2023-07-20"
    },
    {
      "id": "37442d59-8c3c-45c0-8528-01a68d64c63b",
      "name": "Multi-tiered didactic middleware 22",
      "status": "Completed",
      "createdDate": "2025-04-02T20:06:52",
      "updatedDate": "2026-02-06T04:49:07",
      "owner": "Steven Johnson",
      "clientId": "CL-66418",
      "firstName": "Kevin",
      "lastName": "Randall",
      "email": "andrewbailey@example.net",
      "phone": "001-471-825-6053x28956",
      "aum": 12433833.2,
      "riskTolerance": "Moderate",
      "onboardDate": "2021-06-25"
    },
    {
      "id": "83ffbecf-90a7-4d0d-9776-fea1a9ce74b9",
      "name": "Focused non-volatile algorithm 23",
      "status": "Pending",
      "createdDate": "2025-05-29T19:09:15",
      "updatedDate": "2026-02-12T22:47:27",
      "owner": "Jasmine Ball",
      "clientId": "CL-70579",
      "firstName": "Bryan",
      "lastName": "Allen",
      "email": "jennifermora@example.net",
      "phone": "+1-266-511-2444x2173",
      "aum": 14105148.6,
      "riskTolerance": "Conservative",
      "onboardDate": "2025-11-26"
    },
    {
      "id": "7c59d1e5-3418-413f-9be4-20a5237989be",
      "name": "Fully-configurable full-range focus group 24",
      "status": "Completed",
      "createdDate": "2025-09-03T15:53:36",
      "updatedDate": "2026-02-01T22:34:45",
      "owner": "David Johnson",
      "clientId": "CL-54003",
      "firstName": "Teresa",
      "lastName": "Malone",
      "email": "margaret77@example.org",
      "phone": "001-424-908-1544",
      "aum": 11276033.03,
      "riskTolerance": "Moderate",
      "onboardDate": "2021-09-12"
    },
    {
      "id": "13338168-79c5-4256-a596-36cdd51f5c07",
      "name": "Assimilated intangible leverage 25",
      "status": "Completed",
      "createdDate": "2026-01-06T08:07:03",
      "updatedDate": "2026-02-06T07:09:52",
      "owner": "Richard Sanders",
      "clientId": "CL-43698",
      "firstName": "Gabrielle",
      "lastName": "Valdez",
      "email": "james60@example.org",
      "phone": "827.972.4108x0366",
      "aum": 18583131.12,
      "riskTolerance": "Conservative",
      "onboardDate": "2019-09-18"
    }
  ],
  "schema": [
    {
      "fieldName": "id",
      "displayName": "Id",
      "dataType": "string",
      "isKey": true,
      "isRequired": true
    },
    {
      "fieldName": "name",
      "displayName": "Name",
      "dataType": "string",
      "isKey": false,
      "isRequired": true
    },
    {
      "fieldName": "status",
      "displayName": "Status",
      "dataType": "string",
      "isKey": false,
      "isRequired": true
    },
    {
      "fieldName": "createdDate",
      "displayName": "Createddate",
      "dataType": "date",
      "isKey": false,
      "isRequired": false
    },
    {
      "fieldName": "updatedDate",
      "displayName": "Updateddate",
      "dataType": "date",
      "isKey": false,
      "isRequired": false
    },
    {
      "fieldName": "owner",
      "displayName": "Owner",
      "dataType": "string",
      "isKey": false,
      "isRequired": false
    },
    {
      "fieldName": "clientId",
      "displayName": "Clientid",
      "dataType": "string",
      "isKey": false,
      "isRequired": false
    },
    {
      "fieldName": "firstName",
      "displayName": "Firstname",
      "dataType": "string",
      "isKey": false,
      "isRequired": false
    },
    {
      "fieldName": "lastName",
      "displayName": "Lastname",
      "dataType": "string",
      "isKey": false,
      "isRequired": false
    },
    {
      "fieldName": "email",
      "displayName": "Email",
      "dataType": "string",
      "isKey": false,
      "isRequired": false
    },
    {
      "fieldName": "phone",
      "displayName": "Phone",
      "dataType": "string",
      "isKey": false,
      "isRequired": false
    },
    {
      "fieldName": "aum",
      "displayName": "Aum",
      "dataType": "number",
      "isKey": false,
      "isRequired": false
    },
    {
      "fieldName": "riskTolerance",
      "displayName": "Risktolerance",
      "dataType": "string",
      "isKey": false,
      "isRequired": false
    },
    {
      "fieldName": "onboardDate",
      "displayName": "Onboarddate",
      "dataType": "date",
      "isKey": false,
      "isRequired": false
    }
  ]
}