{
  "entityId": "entity-performancereport",
  "queryId": "query-top-performers",
  "totalCount": 59,
  "pageSize": 25,
  "currentPage": 1,
  "records": [
    {
      "id": "7eec7ccb-1d85-41e7-a92f-a1e6fe862a6c",
      "name": "Multi-lateral multi-state superstructure 1",
      "status": "Active",
      "createdDate": "2025-12-15T14:00:02",
      "updatedDate": "2026-02-16T19:26:31",
      "owner": "Dr. Edward Beck",
      "reportId": "RPT-80422",
      "periodStart": "2025-09-24",
      "periodEnd": "2025-12-03",
      "totalReturn": -2.48,
      "benchmark": "60/40 Portfolio",
      "alpha": 1.65,
      "sharpeRatio": 2.41
    },
    {
      "id": "a0709c0f-20b7-4aef-8d1b-4fddbf384268",
      "name": "Automated incremental strategy 2",
      "status": "Active",
      "createdDate": "2025-10-22T17:30:22",
      "updatedDate": "2026-02-05T19:02:30",
      "owner": "Michael Young",
      "reportId": "RPT-67367",
      "periodStart": "2025-11-11",
      "periodEnd": "2025-12-29",
      "totalReturn": 16.95,
      "benchmark": "S&P 500",
      "alpha": -1.01,
      "sharpeRatio": 1.51
    },
    {
      "id": "a1430733-c87c-46c3-8d34-707ab247704b",
      "name": "Vision-oriented scalable implementation 3",
      "status": "Completed",
      "createdDate": "2025-03-10T00:18:10",
      "updatedDate": "2026-02-02T15:18:51",
      "owner": "Keith Mitchell",
      "reportId": "RPT-64250",
      "periodStart": "2025-06-27",
      "periodEnd": "2026-01-15",
      "totalReturn": 15.31,
      "benchmark": "MSCI World",
      "alpha": 0.62,
      "sharpeRatio": 1.69
    },
    {
      "id": "5cb7f087-eafd-43d3-b322-bafe6665faee",
      "name": "Face-to-face modular secured line 4",
      "status": "Pending",
      "createdDate": "2025-05-03T15:30:43",
      "updatedDate": "2026-01-21T15:20:14",
      "owner": "Sarah Smith",
      "reportId": "RPT-33557",
      "periodStart": "2025-06-22",
      "periodEnd": "2026-02-04",
      "totalReturn": 20.8,
      "benchmark": "S&P 500",
      "alpha": -2.12,
      "sharpeRatio": 2.14
    },
    {
      "id": "c4bc7f09-5bf3-43c5-a615-89bdf5b53397",
      "name": "Polarized 6thgeneration utilization 5",
      "status": "Pending",
      "createdDate": "2026-01-17T02:09:16",
      "updatedDate": "2026-02-17T04:49:41",
      "owner": "Edward Pham",
      "reportId": "RPT-25886",
      "periodStart": "2025-08-04",
      "periodEnd": "2025-12-29",
      "totalReturn": 8.65,
      "benchmark": "60/40 Portfolio",
      "alpha": 4.92,
      "sharpeRatio": 2.36
    },
    {
      "id": "c48d1c6e-0c2f-437f-89df-e6cfbf852dd1",
      "name": "Realigned directional conglomeration 6",
      "status": "Inactive",
      "createdDate": "2026-02-13T02:39:24",
      "updatedDate": "2026-02-06T21:26:45",
      "owner": "Michael Downs",
      "reportId": "RPT-41425",
      "periodStart": "2025-04-18",
      "periodEnd": "2025-11-30",
      "totalReturn": 10.09,
      "benchmark": "S&P 500",
      "alpha": -0.32,
      "sharpeRatio": 1.95
    },
    {
      "id": "06bb2b85-5c03-4fe9-a471-bfdeefe4ef5f",
      "name": "Enhanced even-keeled adapter 7",
      "status": "Pending",
      "createdDate": "2025-10-30T00:34:47",
      "updatedDate": "2026-02-09T17:19:03",
      "owner": "Elizabeth Butler",
      "reportId": "RPT-71111",
      "periodStart": "2025-10-23",
      "periodEnd": "2025-12-24",
      "totalReturn": -8.23,
      "benchmark": "Russell 2000",
      "alpha": 2.46,
      "sharpeRatio": 0.79
    },
    {
      "id": "d61ad6da-61b3-4e24-8873-99459168852f",
      "name": "User-friendly executive matrices 8",
      "status": "Inactive",
      "createdDate": "2026-01-20T07:44:39",
      "updatedDate": "2026-01-29T11:46:05",
      "owner": "Frank Wu",
      "reportId": "RPT-40662",
      "periodStart": "2025-04-18",
      "periodEnd": "2026-01-09",
      "totalReturn": -2.61,
      "benchmark": "S&P 500",
      "alpha": 3.23,
      "sharpeRatio": 0.56
    },
    {
      "id": "a2de2555-ffd4-4060-93b4-354da01ef853",
      "name": "Profound 3rdgeneration database 9",
      "status": "Active",
      "createdDate": "2025-12-15T10:34:32",
      "updatedDate": "2026-02-04T05:30:20",
      "owner": "Joseph Brown",
      "reportId": "RPT-41644",
      "periodStart": "2025-07-13",
      "periodEnd": "2026-02-09",
      "totalReturn": 27.67,
      "benchmark": "60/40 Portfolio",
      "alpha": -0.04,
      "sharpeRatio": 1.84
    },
    {
      "id": "f3a045ff-6818-490f-969d-67feba96fdab",
      "name": "Digitized 4thgeneration migration 10",
      "status": "Pending",
      "createdDate": "2026-01-17T13:43:29",
      "updatedDate": "2026-01-20T08:34:52",
      "owner": "Alexis Green",
      "reportId": "RPT-87151",
      "periodStart": "2025-06-04",
      "periodEnd": "2026-02-07",
      "totalReturn": 14.27,
      "benchmark": "Russell 2000",
      "alpha": 2.3,
      "sharpeRatio": 2.49
    },
    {
      "id": "05222d17-9de9-4bca-a5a7-9aeec5b8c5b6",
      "name": "Reduced background model 11",
      "status": "Active",
      "createdDate": "2025-09-27T09:38:31",
      "updatedDate": "2026-02-10T22:12:18",
      "owner": "Kathy Palmer",
      "reportId": "RPT-51328",
      "periodStart": "2025-05-19",
      "periodEnd": "2026-02-09",
      "totalReturn": 3.84,
      "benchmark": "60/40 Portfolio",
      "alpha": -0.89,
      "sharpeRatio": 1.54
    },
    {
      "id": "dc384eff-6a42-48bb-aadb-57ff277c5592",
      "name": "Self-enabling background collaboration 12",
      "status": "Inactive",
      "createdDate": "2025-06-09T21:29:17",
      "updatedDate": "2026-01-27T14:44:43",
      "owner": "Brittney Rodriguez",
      "reportId": "RPT-45017",
      "periodStart": "2025-04-25",
      "periodEnd": "2025-11-27",
      "totalReturn": -6.0,
      "benchmark": "MSCI World",
      "alpha": 1.65,
      "sharpeRatio": 1.76
    },
    {
      "id": "c72445e9-c403-4341-9875-9efa0a9cd838",
      "name": "Multi-channeled even-keeled function 13",
      "status": "Inactive",
      "createdDate": "2025-09-24T06:17:03",
      "updatedDate": "2026-02-12T07:36:10",
      "owner": "Jennifer Thomas",
      "reportId": "RPT-16411",
      "periodStart": "2025-03-14",
      "periodEnd": "2025-12-21",
      "totalReturn": -5.27,
      "benchmark": "60/40 Portfolio",
      "alpha": -1.52,
      "sharpeRatio": 1.53
    },
    {
      "id": "a32b73ed-2018-4e43-96de-338788026008",
      "name": "Enterprise-wide leadingedge protocol 14",
      "status": "Active",
      "createdDate": "2025-06-10T21:06:27",
      "updatedDate": "2026-01-24T23:35:05",
      "owner": "Hunter Clark",
      "reportId": "RPT-97560",
      "periodStart": "2025-05-29",
      "periodEnd": "2026-01-26",
      "totalReturn": 23.97,
      "benchmark": "MSCI World",
      "alpha": -1.75,
      "sharpeRatio": 1.78
    },
    {
      "id": "24b24dc6-5d15-4388-8bc3-46219e430600",
      "name": "Multi-tiered user-facing concept 15",
      "status": "Pending",
      "createdDate": "2025-09-01T18:11:42",
      "updatedDate": "2026-02-07T21:22:45",
      "owner": "Stephanie Cruz",
      "reportId": "RPT-17655",
      "periodStart": "2025-02-16",
      "periodEnd": "2025-12-20",
      "totalReturn": -5.48,
      "benchmark": "MSCI World",
      "alpha": 0.81,
      "sharpeRatio": 0.68
    },
    {
      "id": "ac4ba882-a41a-44b9-a91a-6f8e07841e4e",
      "name": "Upgradable radical budgetary management 16",
      "status": "Completed",
      "createdDate": "2025-07-31T09:49:33",
      "updatedDate": "2026-02-11T14:03:38",
      "owner": "Catherine Donaldson",
      "reportId": "RPT-57652",
      "periodStart": "2025-08-30",
      "periodEnd": "2026-01-30",
      "totalReturn": 30.91,
      "benchmark": "S&P 500",
      "alpha": 1.16,
      "sharpeRatio": 0.5
    },
    {
      "id": "54db767b-95e0-4c10-8f0b-4bd2dc877f0b",
      "name": "Progressive human-resource approach 17",
      "status": "Completed",
      "createdDate": "2025-08-13T15:31:39",
      "updatedDate": "2026-02-01T03:52:24",
      "owner": "Laura Hill",
      "reportId": "RPT-85966",
      "periodStart": "2025-10-14",
      "periodEnd": "2026-01-07",
      "totalReturn": 25.62,
      "benchmark": "Russell 2000",
      "alpha": 4.97,
      "sharpeRatio": 0.64
    },
    {
      "id": "d95f5af9-3f3a-49c0-80e4-5a7db6eb7cd4",
      "name": "Re-contextualized bi-directional ability 18",
      "status": "Pending",
      "createdDate": "2025-06-22T12:28:50",
      "updatedDate": "2026-02-08T05:27:33",
      "owner": "Michele Ryan",
      "reportId": "RPT-84954",
      "periodStart": "2025-04-14",
      "periodEnd": "2025-12-03",
      "totalReturn": 24.11,
      "benchmark": "S&P 500",
      "alpha": 3.35,
      "sharpeRatio": 1.21
    },
    {
      "id": "733daed8-bc70-47c6-be63-bc706418f890",
      "name": "Monitored stable open system 19",
      "status": "Pending",
      "createdDate": "2025-03-17T16:01:02",
      "updatedDate": "2026-02-07T07:04:44",
      "owner": "Lisa Johnson",
      "reportId": "RPT-32783",
      "periodStart": "2025-11-03",
      "periodEnd": "2026-01-09",
      "totalReturn": 0.82,
      "benchmark": "S&P 500",
      "alpha": 1.64,
      "sharpeRatio": 1.29
    },
    {
      "id": "287faa54-ce93-4c3c-b860-b6f73247afd0",
      "name": "Multi-layered zero administration capacity 20",
      "status": "Inactive",
      "createdDate": "2025-11-11T04:48:21",
      "updatedDate": "2026-01-28T22:40:51",
      "owner": "Ashley Mata DDS",
      "reportId": "RPT-47259",
      "periodStart": "2025-09-10",
      "periodEnd": "2026-01-18",
      "totalReturn": 4.21,
      "benchmark": "Russell 2000",
      "alpha": -1.99,
      "sharpeRatio": 2.49
    },
    {
      "id": "961381ed-d313-4c9e-a8ea-c3735abd3eef",
      "name": "Profound explicit software 21",
      "status": "Pending",
      "createdDate": "2025-03-14T17:32:25",
      "updatedDate": "2026-01-19T02:55:03",
      "owner": "Troy Murray",
      "reportId": "RPT-21118",
      "periodStart": "2025-09-19",
      "periodEnd": "2026-01-03",
      "totalReturn": 11.94,
      "benchmark": "S&P 500",
      "alpha": 0.64,
      "sharpeRatio": 1.51
    },
    {
      "id": "d345f05c-60c8-4318-8f46-be8c58c7d8a2",
      "name": "Programmable hybrid methodology 22",
      "status": "Pending",
      "createdDate": "2025-04-08T03:17:43",
      "updatedDate": "2026-02-13T23:58:40",
      "owner": "Lee Vang",
      "reportId": "RPT-58803",
      "periodStart": "2025-03-09",
      "periodEnd": "2025-11-30",
      "totalReturn": -5.95,
      "benchmark": "S&P 500",
      "alpha": 2.92,
      "sharpeRatio": 1.54
    },
    {
      "id": "a79205ba-a757-4127-8e8f-077ceceae58a",
      "name": "Reactive national model 23",
      "status": "Completed",
      "createdDate": "2025-07-07T13:57:05",
      "updatedDate": "2026-02-11T14:32:49",
      "owner": "Kimberly Campbell",
      "reportId": "RPT-18976",
      "periodStart": "2025-03-16",
      "periodEnd": "2025-12-13",
      "totalReturn": 22.3,
      "benchmark": "S&P 500",
      "alpha": 2.5,
      "sharpeRatio": 1.22
    },
    {
      "id": "1bd8875e-e230-4fa4-b35a-83991d592f3c",
      "name": "Optional 4thgeneration customer loyalty 24",
      "status": "Pending",
      "createdDate": "2025-06-15T14:43:07",
      "updatedDate": "2026-01-22T14:17:49",
      "owner": "Roy Williams",
      "reportId": "RPT-55537",
      "periodStart": "2025-10-12",
      "periodEnd": "2026-02-04",
      "totalReturn": 1.25,
      "benchmark": "60/40 Portfolio",
      "alpha": 4.83,
      "sharpeRatio": 2.2
    },
    {
      "id": "60e3f9cd-6b29-4dd6-b9fb-00bb242b450c",
      "name": "Advanced user-facing adapter 25",
      "status": "Completed",
      "createdDate": "2025-04-06T05:20:23",
      "updatedDate": "2026-01-28T21:36:56",
      "owner": "Henry Graham",
      "reportId": "RPT-22823",
      "periodStart": "2025-04-13",
      "periodEnd": "2026-01-22",
      "totalReturn": 21.56,
      "benchmark": "Russell 2000",
      "alpha": -1.55,
      "sharpeRatio": 2.43
    }
  ],
  "schema": [
    {
      "fieldName": "id",
      "displayName": "Id",
      "dataType": "string",
      "isKey": true,
      "isRequired": true
    },
    {
      "fieldName": "name",
      "displayName": "Name",
      "dataType": "string",
      "isKey": false,
      "isRequired": true
    },
    {
      "fieldName": "status",
      "displayName": "Status",
      "dataType": "string",
      "isKey": false,
      "isRequired": true
    },
    {
      "fieldName": "createdDate",
      "displayName": "Createddate",
      "dataType": "date",
      "isKey": false,
      "isRequired": false
    },
    {
      "fieldName": "updatedDate",
      "displayName": "Updateddate",
      "dataType": "date",
      "isKey": false,
      "isRequired": false
    },
    {
      "fieldName": "owner",
      "displayName": "Owner",
      "dataType": "string",
      "isKey": false,
      "isRequired": false
    },
    {
      "fieldName": "reportId",
      "displayName": "Reportid",
      "dataType": "string",
      "isKey": false,
      "isRequired": false
    },
    {
      "fieldName": "periodStart",
      "displayName": "Periodstart",
      "dataType": "date",
      "isKey": false,
      "isRequired": false
    },
    {
      "fieldName": "periodEnd",
      "displayName": "Periodend",
      "dataType": "date",
      "isKey": false,
      "isRequired": false
    },
    {
      "fieldName": "totalReturn",
      "displayName": "Totalreturn",
      "dataType": "number",
      "isKey": false,
      "isRequired": false
    },
    {
      "fieldName": "benchmark",
      "displayName": "Benchmark",
      "dataType": "string",
      "isKey": false,
      "isRequired": false
    },
    {
      "fieldName": "alpha",
      "displayName": "Alpha",
      "dataType": "number",
      "isKey": false,
      "isRequired": false
    },
    {
      "fieldName": "sharpeRatio",
      "displayName": "Sharperatio",
      "dataType": "number",
      "isKey": false,
      "isRequired": false
    }
  ]
}